[
    {
        "login": "chris-rock",
        "avatar_url": "https://avatars3.githubusercontent.com/u/1178413?v=4",
        "url": "https://api.github.com/users/chris-rock",
        "contributions": 1164
    },
    {
        "login": "arlimus",
        "avatar_url": "https://avatars0.githubusercontent.com/u/1307529?v=4",
        "url": "https://api.github.com/users/arlimus",
        "contributions": 984
    },
    {
        "login": "atomic111",
        "avatar_url": "https://avatars3.githubusercontent.com/u/7220740?v=4",
        "url": "https://api.github.com/users/atomic111",
        "contributions": 605
    },
    {
        "login": "ehaselwanter",
        "avatar_url": "https://avatars2.githubusercontent.com/u/18671?v=4",
        "url": "https://api.github.com/users/ehaselwanter",
        "contributions": 467
    },
    {
        "login": "artem-sidorenko",
        "avatar_url": "https://avatars2.githubusercontent.com/u/1645670?v=4",
        "url": "https://api.github.com/users/artem-sidorenko",
        "contributions": 268
    },
    {
        "login": "rndmh3ro",
        "avatar_url": "https://avatars0.githubusercontent.com/u/3198961?v=4",
        "url": "https://api.github.com/users/rndmh3ro",
        "contributions": 183
    },
    {
        "login": "bkw",
        "avatar_url": "https://avatars2.githubusercontent.com/u/60910?v=4",
        "url": "https://api.github.com/users/bkw",
        "contributions": 130
    },
    {
        "login": "shortdudey123",
        "avatar_url": "https://avatars1.githubusercontent.com/u/3051981?v=4",
        "url": "https://api.github.com/users/shortdudey123",
        "contributions": 56
    },
    {
        "login": "mcgege",
        "avatar_url": "https://avatars1.githubusercontent.com/u/6241510?v=4",
        "url": "https://api.github.com/users/mcgege",
        "contributions": 50
    },
    {
        "login": "rarenerd",
        "avatar_url": "https://avatars1.githubusercontent.com/u/976339?v=4",
        "url": "https://api.github.com/users/rarenerd",
        "contributions": 35
    },
    {
        "login": "fitz123",
        "avatar_url": "https://avatars3.githubusercontent.com/u/10243861?v=4",
        "url": "https://api.github.com/users/fitz123",
        "contributions": 33
    },
    {
        "login": "grdnrio",
        "avatar_url": "https://avatars2.githubusercontent.com/u/2278161?v=4",
        "url": "https://api.github.com/users/grdnrio",
        "contributions": 32
    },
    {
        "login": "juju4",
        "avatar_url": "https://avatars1.githubusercontent.com/u/1300844?v=4",
        "url": "https://api.github.com/users/juju4",
        "contributions": 25
    },
    {
        "login": "tas50",
        "avatar_url": "https://avatars1.githubusercontent.com/u/1015200?v=4",
        "url": "https://api.github.com/users/tas50",
        "contributions": 20
    },
    {
        "login": "jcheroske",
        "avatar_url": "https://avatars2.githubusercontent.com/u/3675338?v=4",
        "url": "https://api.github.com/users/jcheroske",
        "contributions": 18
    },
    {
        "login": "alexpop",
        "avatar_url": "https://avatars0.githubusercontent.com/u/107378?v=4",
        "url": "https://api.github.com/users/alexpop",
        "contributions": 17
    },
    {
        "login": "timstoop",
        "avatar_url": "https://avatars2.githubusercontent.com/u/729432?v=4",
        "url": "https://api.github.com/users/timstoop",
        "contributions": 14
    },
    {
        "login": "supergicko",
        "avatar_url": "https://avatars2.githubusercontent.com/u/8234898?v=4",
        "url": "https://api.github.com/users/supergicko",
        "contributions": 13
    },
    {
        "login": "conorsch",
        "avatar_url": "https://avatars0.githubusercontent.com/u/657862?v=4",
        "url": "https://api.github.com/users/conorsch",
        "contributions": 12
    },
    {
        "login": "Rockstar04",
        "avatar_url": "https://avatars3.githubusercontent.com/u/641721?v=4",
        "url": "https://api.github.com/users/Rockstar04",
        "contributions": 12
    },
    {
        "login": "lazzurs",
        "avatar_url": "https://avatars3.githubusercontent.com/u/15793?v=4",
        "url": "https://api.github.com/users/lazzurs",
        "contributions": 12
    },
    {
        "login": "a-tom",
        "avatar_url": "https://avatars1.githubusercontent.com/u/11059248?v=4",
        "url": "https://api.github.com/users/a-tom",
        "contributions": 11
    },
    {
        "login": "michaelkrieg",
        "avatar_url": "https://avatars3.githubusercontent.com/u/283142?v=4",
        "url": "https://api.github.com/users/michaelkrieg",
        "contributions": 10
    },
    {
        "login": "bitvijays",
        "avatar_url": "https://avatars2.githubusercontent.com/u/9039339?v=4",
        "url": "https://api.github.com/users/bitvijays",
        "contributions": 9
    },
    {
        "login": "foonix",
        "avatar_url": "https://avatars2.githubusercontent.com/u/1442578?v=4",
        "url": "https://api.github.com/users/foonix",
        "contributions": 7
    },
    {
        "login": "enemarke",
        "avatar_url": "https://avatars2.githubusercontent.com/u/4777514?v=4",
        "url": "https://api.github.com/users/enemarke",
        "contributions": 7
    },
    {
        "login": "3flex",
        "avatar_url": "https://avatars2.githubusercontent.com/u/170028?v=4",
        "url": "https://api.github.com/users/3flex",
        "contributions": 7
    },
    {
        "login": "jmara",
        "avatar_url": "https://avatars3.githubusercontent.com/u/972041?v=4",
        "url": "https://api.github.com/users/jmara",
        "contributions": 7
    },
    {
        "login": "techraf",
        "avatar_url": "https://avatars1.githubusercontent.com/u/1206173?v=4",
        "url": "https://api.github.com/users/techraf",
        "contributions": 7
    },
    {
        "login": "fazlearefin",
        "avatar_url": "https://avatars3.githubusercontent.com/u/1625934?v=4",
        "url": "https://api.github.com/users/fazlearefin",
        "contributions": 6
    },
    {
        "login": "ncs-alane",
        "avatar_url": "https://avatars0.githubusercontent.com/u/17574503?v=4",
        "url": "https://api.github.com/users/ncs-alane",
        "contributions": 6
    },
    {
        "login": "jbronn",
        "avatar_url": "https://avatars2.githubusercontent.com/u/141748?v=4",
        "url": "https://api.github.com/users/jbronn",
        "contributions": 6
    },
    {
        "login": "lubomir-kacalek",
        "avatar_url": "https://avatars2.githubusercontent.com/u/26789632?v=4",
        "url": "https://api.github.com/users/lubomir-kacalek",
        "contributions": 6
    },
    {
        "login": "trumant",
        "avatar_url": "https://avatars1.githubusercontent.com/u/599706?v=4",
        "url": "https://api.github.com/users/trumant",
        "contributions": 6
    },
    {
        "login": "igoraj",
        "avatar_url": "https://avatars3.githubusercontent.com/u/1874763?v=4",
        "url": "https://api.github.com/users/igoraj",
        "contributions": 6
    },
    {
        "login": "martinbydefault",
        "avatar_url": "https://avatars3.githubusercontent.com/u/25038813?v=4",
        "url": "https://api.github.com/users/martinbydefault",
        "contributions": 5
    },
    {
        "login": "tuxmea",
        "avatar_url": "https://avatars3.githubusercontent.com/u/763214?v=4",
        "url": "https://api.github.com/users/tuxmea",
        "contributions": 5
    },
    {
        "login": "cdenneen",
        "avatar_url": "https://avatars0.githubusercontent.com/u/720097?v=4",
        "url": "https://api.github.com/users/cdenneen",
        "contributions": 5
    },
    {
        "login": "kurthuwig",
        "avatar_url": "https://avatars1.githubusercontent.com/u/2757758?v=4",
        "url": "https://api.github.com/users/kurthuwig",
        "contributions": 5
    },
    {
        "login": "tsenart",
        "avatar_url": "https://avatars2.githubusercontent.com/u/67471?v=4",
        "url": "https://api.github.com/users/tsenart",
        "contributions": 4
    },
    {
        "login": "jbenden",
        "avatar_url": "https://avatars3.githubusercontent.com/u/73767?v=4",
        "url": "https://api.github.com/users/jbenden",
        "contributions": 4
    },
    {
        "login": "aried3r",
        "avatar_url": "https://avatars1.githubusercontent.com/u/1301152?v=4",
        "url": "https://api.github.com/users/aried3r",
        "contributions": 4
    },
    {
        "login": "shoekstra",
        "avatar_url": "https://avatars1.githubusercontent.com/u/3757382?v=4",
        "url": "https://api.github.com/users/shoekstra",
        "contributions": 4
    },
    {
        "login": "Normo",
        "avatar_url": "https://avatars3.githubusercontent.com/u/2527899?v=4",
        "url": "https://api.github.com/users/Normo",
        "contributions": 4
    },
    {
        "login": "netflash",
        "avatar_url": "https://avatars1.githubusercontent.com/u/2478391?v=4",
        "url": "https://api.github.com/users/netflash",
        "contributions": 4
    },
    {
        "login": "ypid",
        "avatar_url": "https://avatars0.githubusercontent.com/u/1301158?v=4",
        "url": "https://api.github.com/users/ypid",
        "contributions": 4
    },
    {
        "login": "alval5280",
        "avatar_url": "https://avatars2.githubusercontent.com/u/36253190?v=4",
        "url": "https://api.github.com/users/alval5280",
        "contributions": 4
    },
    {
        "login": "rapenchukd",
        "avatar_url": "https://avatars1.githubusercontent.com/u/8246841?v=4",
        "url": "https://api.github.com/users/rapenchukd",
        "contributions": 4
    },
    {
        "login": "patcon",
        "avatar_url": "https://avatars2.githubusercontent.com/u/305339?v=4",
        "url": "https://api.github.com/users/patcon",
        "contributions": 4
    },
    {
        "login": "woneill",
        "avatar_url": "https://avatars1.githubusercontent.com/u/1393558?v=4",
        "url": "https://api.github.com/users/woneill",
        "contributions": 4
    },
    {
        "login": "edtubillara",
        "avatar_url": "https://avatars3.githubusercontent.com/u/3075007?v=4",
        "url": "https://api.github.com/users/edtubillara",
        "contributions": 4
    },
    {
        "login": "HenryTheHamster",
        "avatar_url": "https://avatars2.githubusercontent.com/u/1962362?v=4",
        "url": "https://api.github.com/users/HenryTheHamster",
        "contributions": 4
    },
    {
        "login": "yvovandoorn",
        "avatar_url": "https://avatars1.githubusercontent.com/u/2694655?v=4",
        "url": "https://api.github.com/users/yvovandoorn",
        "contributions": 4
    },
    {
        "login": "dupuy",
        "avatar_url": "https://avatars0.githubusercontent.com/u/33216?v=4",
        "url": "https://api.github.com/users/dupuy",
        "contributions": 3
    },
    {
        "login": "oakey-b1",
        "avatar_url": "https://avatars1.githubusercontent.com/u/14907501?v=4",
        "url": "https://api.github.com/users/oakey-b1",
        "contributions": 3
    },
    {
        "login": "timogoebel",
        "avatar_url": "https://avatars0.githubusercontent.com/u/4107560?v=4",
        "url": "https://api.github.com/users/timogoebel",
        "contributions": 3
    },
    {
        "login": "crashdummymch",
        "avatar_url": "https://avatars0.githubusercontent.com/u/1964458?v=4",
        "url": "https://api.github.com/users/crashdummymch",
        "contributions": 3
    },
    {
        "login": "mattlqx",
        "avatar_url": "https://avatars0.githubusercontent.com/u/739851?v=4",
        "url": "https://api.github.com/users/mattlqx",
        "contributions": 3
    },
    {
        "login": "mikemoate",
        "avatar_url": "https://avatars3.githubusercontent.com/u/14893352?v=4",
        "url": "https://api.github.com/users/mikemoate",
        "contributions": 3
    },
    {
        "login": "emilyh315",
        "avatar_url": "https://avatars0.githubusercontent.com/u/23243839?v=4",
        "url": "https://api.github.com/users/emilyh315",
        "contributions": 3
    },
    {
        "login": "ageis",
        "avatar_url": "https://avatars0.githubusercontent.com/u/1161532?v=4",
        "url": "https://api.github.com/users/ageis",
        "contributions": 3
    },
    {
        "login": "fullyint",
        "avatar_url": "https://avatars1.githubusercontent.com/u/7338513?v=4",
        "url": "https://api.github.com/users/fullyint",
        "contributions": 3
    },
    {
        "login": "pwyliu",
        "avatar_url": "https://avatars3.githubusercontent.com/u/3036782?v=4",
        "url": "https://api.github.com/users/pwyliu",
        "contributions": 3
    },
    {
        "login": "hdep",
        "avatar_url": "https://avatars2.githubusercontent.com/u/12408502?v=4",
        "url": "https://api.github.com/users/hdep",
        "contributions": 3
    },
    {
        "login": "attachmentgenie",
        "avatar_url": "https://avatars0.githubusercontent.com/u/163633?v=4",
        "url": "https://api.github.com/users/attachmentgenie",
        "contributions": 3
    },
    {
        "login": "dmerrick",
        "avatar_url": "https://avatars2.githubusercontent.com/u/49680?v=4",
        "url": "https://api.github.com/users/dmerrick",
        "contributions": 3
    },
    {
        "login": "mburns",
        "avatar_url": "https://avatars1.githubusercontent.com/u/5170?v=4",
        "url": "https://api.github.com/users/mburns",
        "contributions": 2
    },
    {
        "login": "fheinle",
        "avatar_url": "https://avatars0.githubusercontent.com/u/371610?v=4",
        "url": "https://api.github.com/users/fheinle",
        "contributions": 2
    },
    {
        "login": "coolguru",
        "avatar_url": "https://avatars1.githubusercontent.com/u/543930?v=4",
        "url": "https://api.github.com/users/coolguru",
        "contributions": 2
    },
    {
        "login": "tstuber",
        "avatar_url": "https://avatars3.githubusercontent.com/u/2261363?v=4",
        "url": "https://api.github.com/users/tstuber",
        "contributions": 2
    },
    {
        "login": "szEvEz",
        "avatar_url": "https://avatars2.githubusercontent.com/u/17480438?v=4",
        "url": "https://api.github.com/users/szEvEz",
        "contributions": 2
    },
    {
        "login": "duk3luk3",
        "avatar_url": "https://avatars2.githubusercontent.com/u/611471?v=4",
        "url": "https://api.github.com/users/duk3luk3",
        "contributions": 2
    },
    {
        "login": "thomasjpfan",
        "avatar_url": "https://avatars2.githubusercontent.com/u/5402633?v=4",
        "url": "https://api.github.com/users/thomasjpfan",
        "contributions": 2
    },
    {
        "login": "rdeusser",
        "avatar_url": "https://avatars2.githubusercontent.com/u/5935071?v=4",
        "url": "https://api.github.com/users/rdeusser",
        "contributions": 2
    },
    {
        "login": "jerryaldrichiii",
        "avatar_url": "https://avatars2.githubusercontent.com/u/13783510?v=4",
        "url": "https://api.github.com/users/jerryaldrichiii",
        "contributions": 2
    },
    {
        "login": "srenatus",
        "avatar_url": "https://avatars3.githubusercontent.com/u/870638?v=4",
        "url": "https://api.github.com/users/srenatus",
        "contributions": 2
    },
    {
        "login": "cjsheets",
        "avatar_url": "https://avatars3.githubusercontent.com/u/3053829?v=4",
        "url": "https://api.github.com/users/cjsheets",
        "contributions": 2
    },
    {
        "login": "narengan",
        "avatar_url": "https://avatars2.githubusercontent.com/u/7330077?v=4",
        "url": "https://api.github.com/users/narengan",
        "contributions": 2
    },
    {
        "login": "colin-nolan",
        "avatar_url": "https://avatars1.githubusercontent.com/u/1138107?v=4",
        "url": "https://api.github.com/users/colin-nolan",
        "contributions": 2
    },
    {
        "login": "operatingops",
        "avatar_url": "https://avatars0.githubusercontent.com/u/22417133?v=4",
        "url": "https://api.github.com/users/operatingops",
        "contributions": 2
    },
    {
        "login": "bazbremner",
        "avatar_url": "https://avatars1.githubusercontent.com/u/173771?v=4",
        "url": "https://api.github.com/users/bazbremner",
        "contributions": 2
    },
    {
        "login": "rediculum",
        "avatar_url": "https://avatars3.githubusercontent.com/u/8666333?v=4",
        "url": "https://api.github.com/users/rediculum",
        "contributions": 2
    },
    {
        "login": "SteveLowe",
        "avatar_url": "https://avatars2.githubusercontent.com/u/8172815?v=4",
        "url": "https://api.github.com/users/SteveLowe",
        "contributions": 2
    },
    {
        "login": "bdwyertech",
        "avatar_url": "https://avatars3.githubusercontent.com/u/2973273?v=4",
        "url": "https://api.github.com/users/bdwyertech",
        "contributions": 2
    },
    {
        "login": "iennae",
        "avatar_url": "https://avatars2.githubusercontent.com/u/1592404?v=4",
        "url": "https://api.github.com/users/iennae",
        "contributions": 2
    },
    {
        "login": "ekelson-bcove",
        "avatar_url": "https://avatars1.githubusercontent.com/u/20729707?v=4",
        "url": "https://api.github.com/users/ekelson-bcove",
        "contributions": 2
    },
    {
        "login": "MattTunny",
        "avatar_url": "https://avatars2.githubusercontent.com/u/15994365?v=4",
        "url": "https://api.github.com/users/MattTunny",
        "contributions": 2
    },
    {
        "login": "ftaeger",
        "avatar_url": "https://avatars1.githubusercontent.com/u/17875285?v=4",
        "url": "https://api.github.com/users/ftaeger",
        "contributions": 2
    },
    {
        "login": "rooprob",
        "avatar_url": "https://avatars2.githubusercontent.com/u/124807?v=4",
        "url": "https://api.github.com/users/rooprob",
        "contributions": 2
    },
    {
        "login": "tprobinson",
        "avatar_url": "https://avatars0.githubusercontent.com/u/13907373?v=4",
        "url": "https://api.github.com/users/tprobinson",
        "contributions": 2
    },
    {
        "login": "bernhardschmidt",
        "avatar_url": "https://avatars1.githubusercontent.com/u/772230?v=4",
        "url": "https://api.github.com/users/bernhardschmidt",
        "contributions": 2
    },
    {
        "login": "enzor",
        "avatar_url": "https://avatars1.githubusercontent.com/u/73625?v=4",
        "url": "https://api.github.com/users/enzor",
        "contributions": 2
    },
    {
        "login": "avanier",
        "avatar_url": "https://avatars2.githubusercontent.com/u/4009658?v=4",
        "url": "https://api.github.com/users/avanier",
        "contributions": 2
    },
    {
        "login": "aschmidt75",
        "avatar_url": "https://avatars3.githubusercontent.com/u/2517871?v=4",
        "url": "https://api.github.com/users/aschmidt75",
        "contributions": 2
    },
    {
        "login": "tyrken",
        "avatar_url": "https://avatars1.githubusercontent.com/u/2693365?v=4",
        "url": "https://api.github.com/users/tyrken",
        "contributions": 1
    },
    {
        "login": "vivekagr",
        "avatar_url": "https://avatars2.githubusercontent.com/u/3046787?v=4",
        "url": "https://api.github.com/users/vivekagr",
        "contributions": 1
    },
    {
        "login": "elijah",
        "avatar_url": "https://avatars2.githubusercontent.com/u/43155?v=4",
        "url": "https://api.github.com/users/elijah",
        "contributions": 1
    },
    {
        "login": "jklare",
        "avatar_url": "https://avatars0.githubusercontent.com/u/3672559?v=4",
        "url": "https://api.github.com/users/jklare",
        "contributions": 1
    },
    {
        "login": "pestaa",
        "avatar_url": "https://avatars3.githubusercontent.com/u/187342?v=4",
        "url": "https://api.github.com/users/pestaa",
        "contributions": 1
    },
    {
        "login": "ascendantlogic",
        "avatar_url": "https://avatars3.githubusercontent.com/u/60331?v=4",
        "url": "https://api.github.com/users/ascendantlogic",
        "contributions": 1
    },
    {
        "login": "michaelklishin",
        "avatar_url": "https://avatars3.githubusercontent.com/u/1090?v=4",
        "url": "https://api.github.com/users/michaelklishin",
        "contributions": 1
    },
    {
        "login": "sirkkalap",
        "avatar_url": "https://avatars2.githubusercontent.com/u/703699?v=4",
        "url": "https://api.github.com/users/sirkkalap",
        "contributions": 1
    },
    {
        "login": "runningman84",
        "avatar_url": "https://avatars2.githubusercontent.com/u/1699128?v=4",
        "url": "https://api.github.com/users/runningman84",
        "contributions": 1
    },
    {
        "login": "sidxz",
        "avatar_url": "https://avatars2.githubusercontent.com/u/11301077?v=4",
        "url": "https://api.github.com/users/sidxz",
        "contributions": 1
    },
    {
        "login": "kabakakao",
        "avatar_url": "https://avatars1.githubusercontent.com/u/18161756?v=4",
        "url": "https://api.github.com/users/kabakakao",
        "contributions": 1
    },
    {
        "login": "zachallett",
        "avatar_url": "https://avatars2.githubusercontent.com/u/1425271?v=4",
        "url": "https://api.github.com/users/zachallett",
        "contributions": 1
    },
    {
        "login": "bpieck",
        "avatar_url": "https://avatars2.githubusercontent.com/u/1452390?v=4",
        "url": "https://api.github.com/users/bpieck",
        "contributions": 1
    },
    {
        "login": "JackChance",
        "avatar_url": "https://avatars1.githubusercontent.com/u/7656515?v=4",
        "url": "https://api.github.com/users/JackChance",
        "contributions": 1
    },
    {
        "login": "jdoss",
        "avatar_url": "https://avatars0.githubusercontent.com/u/8195?v=4",
        "url": "https://api.github.com/users/jdoss",
        "contributions": 1
    },
    {
        "login": "simfish85",
        "avatar_url": "https://avatars2.githubusercontent.com/u/11316707?v=4",
        "url": "https://api.github.com/users/simfish85",
        "contributions": 1
    },
    {
        "login": "thomasrg",
        "avatar_url": "https://avatars2.githubusercontent.com/u/1976625?v=4",
        "url": "https://api.github.com/users/thomasrg",
        "contributions": 1
    },
    {
        "login": "rveznaver",
        "avatar_url": "https://avatars3.githubusercontent.com/u/901006?v=4",
        "url": "https://api.github.com/users/rveznaver",
        "contributions": 1
    },
    {
        "login": "rojomisin",
        "avatar_url": "https://avatars2.githubusercontent.com/u/3313148?v=4",
        "url": "https://api.github.com/users/rojomisin",
        "contributions": 1
    },
    {
        "login": "fti7",
        "avatar_url": "https://avatars2.githubusercontent.com/u/7014664?v=4",
        "url": "https://api.github.com/users/fti7",
        "contributions": 1
    },
    {
        "login": "gtz42",
        "avatar_url": "https://avatars1.githubusercontent.com/u/1958999?v=4",
        "url": "https://api.github.com/users/gtz42",
        "contributions": 1
    },
    {
        "login": "itoperatorguy",
        "avatar_url": "https://avatars1.githubusercontent.com/u/6641365?v=4",
        "url": "https://api.github.com/users/itoperatorguy",
        "contributions": 1
    },
    {
        "login": "veetow",
        "avatar_url": "https://avatars2.githubusercontent.com/u/532727?v=4",
        "url": "https://api.github.com/users/veetow",
        "contributions": 1
    },
    {
        "login": "shirokatze",
        "avatar_url": "https://avatars2.githubusercontent.com/u/2309387?v=4",
        "url": "https://api.github.com/users/shirokatze",
        "contributions": 1
    },
    {
        "login": "MagnusEnger",
        "avatar_url": "https://avatars1.githubusercontent.com/u/13331?v=4",
        "url": "https://api.github.com/users/MagnusEnger",
        "contributions": 1
    },
    {
        "login": "Nowheresly",
        "avatar_url": "https://avatars0.githubusercontent.com/u/916109?v=4",
        "url": "https://api.github.com/users/Nowheresly",
        "contributions": 1
    },
    {
        "login": "kivilahtio",
        "avatar_url": "https://avatars1.githubusercontent.com/u/12710433?v=4",
        "url": "https://api.github.com/users/kivilahtio",
        "contributions": 1
    },
    {
        "login": "ruettimac",
        "avatar_url": "https://avatars3.githubusercontent.com/u/2353146?v=4",
        "url": "https://api.github.com/users/ruettimac",
        "contributions": 1
    },
    {
        "login": "espoelstra",
        "avatar_url": "https://avatars0.githubusercontent.com/u/7798975?v=4",
        "url": "https://api.github.com/users/espoelstra",
        "contributions": 1
    },
    {
        "login": "bachp",
        "avatar_url": "https://avatars1.githubusercontent.com/u/333807?v=4",
        "url": "https://api.github.com/users/bachp",
        "contributions": 1
    },
    {
        "login": "rcII",
        "avatar_url": "https://avatars3.githubusercontent.com/u/36416768?v=4",
        "url": "https://api.github.com/users/rcII",
        "contributions": 1
    },
    {
        "login": "hyrsky",
        "avatar_url": "https://avatars0.githubusercontent.com/u/732227?v=4",
        "url": "https://api.github.com/users/hyrsky",
        "contributions": 1
    },
    {
        "login": "stenwt",
        "avatar_url": "https://avatars1.githubusercontent.com/u/149782?v=4",
        "url": "https://api.github.com/users/stenwt",
        "contributions": 1
    },
    {
        "login": "aavetis",
        "avatar_url": "https://avatars3.githubusercontent.com/u/3076502?v=4",
        "url": "https://api.github.com/users/aavetis",
        "contributions": 1
    },
    {
        "login": "strangeman",
        "avatar_url": "https://avatars3.githubusercontent.com/u/1083576?v=4",
        "url": "https://api.github.com/users/strangeman",
        "contributions": 1
    },
    {
        "login": "james-stocks",
        "avatar_url": "https://avatars1.githubusercontent.com/u/12136665?v=4",
        "url": "https://api.github.com/users/james-stocks",
        "contributions": 1
    },
    {
        "login": "zbrojny120",
        "avatar_url": "https://avatars0.githubusercontent.com/u/14238119?v=4",
        "url": "https://api.github.com/users/zbrojny120",
        "contributions": 1
    },
    {
        "login": "juliandunn",
        "avatar_url": "https://avatars3.githubusercontent.com/u/841412?v=4",
        "url": "https://api.github.com/users/juliandunn",
        "contributions": 1
    },
    {
        "login": "lnxchk",
        "avatar_url": "https://avatars0.githubusercontent.com/u/588600?v=4",
        "url": "https://api.github.com/users/lnxchk",
        "contributions": 1
    },
    {
        "login": "marcelhuth",
        "avatar_url": "https://avatars2.githubusercontent.com/u/9551108?v=4",
        "url": "https://api.github.com/users/marcelhuth",
        "contributions": 1
    },
    {
        "login": "tomhaynes",
        "avatar_url": "https://avatars3.githubusercontent.com/u/24224506?v=4",
        "url": "https://api.github.com/users/tomhaynes",
        "contributions": 1
    },
    {
        "login": "aaronlippold",
        "avatar_url": "https://avatars3.githubusercontent.com/u/1486440?v=4",
        "url": "https://api.github.com/users/aaronlippold",
        "contributions": 1
    },
    {
        "login": "iveskins",
        "avatar_url": "https://avatars3.githubusercontent.com/u/18106420?v=4",
        "url": "https://api.github.com/users/iveskins",
        "contributions": 1
    },
    {
        "login": "pbanderas",
        "avatar_url": "https://avatars0.githubusercontent.com/u/4366475?v=4",
        "url": "https://api.github.com/users/pbanderas",
        "contributions": 1
    },
    {
        "login": "AnMoeller",
        "avatar_url": "https://avatars1.githubusercontent.com/u/31211542?v=4",
        "url": "https://api.github.com/users/AnMoeller",
        "contributions": 1
    },
    {
        "login": "syhe",
        "avatar_url": "https://avatars2.githubusercontent.com/u/10154867?v=4",
        "url": "https://api.github.com/users/syhe",
        "contributions": 1
    },
    {
        "login": "dhohengassner",
        "avatar_url": "https://avatars3.githubusercontent.com/u/34940716?v=4",
        "url": "https://api.github.com/users/dhohengassner",
        "contributions": 1
    },
    {
        "login": "jjasghar",
        "avatar_url": "https://avatars0.githubusercontent.com/u/810824?v=4",
        "url": "https://api.github.com/users/jjasghar",
        "contributions": 1
    },
    {
        "login": "TLoebner",
        "avatar_url": "https://avatars3.githubusercontent.com/u/3961869?v=4",
        "url": "https://api.github.com/users/TLoebner",
        "contributions": 1
    },
    {
        "login": "ojongerius",
        "avatar_url": "https://avatars0.githubusercontent.com/u/1726055?v=4",
        "url": "https://api.github.com/users/ojongerius",
        "contributions": 1
    },
    {
        "login": "pmav99",
        "avatar_url": "https://avatars0.githubusercontent.com/u/411196?v=4",
        "url": "https://api.github.com/users/pmav99",
        "contributions": 1
    },
    {
        "login": "joshmyers",
        "avatar_url": "https://avatars1.githubusercontent.com/u/3025844?v=4",
        "url": "https://api.github.com/users/joshmyers",
        "contributions": 1
    },
    {
        "login": "eyespies",
        "avatar_url": "https://avatars2.githubusercontent.com/u/1528865?v=4",
        "url": "https://api.github.com/users/eyespies",
        "contributions": 1
    },
    {
        "login": "jaksi",
        "avatar_url": "https://avatars2.githubusercontent.com/u/479446?v=4",
        "url": "https://api.github.com/users/jaksi",
        "contributions": 1
    },
    {
        "login": "towo",
        "avatar_url": "https://avatars2.githubusercontent.com/u/271819?v=4",
        "url": "https://api.github.com/users/towo",
        "contributions": 1
    },
    {
        "login": "kekumu",
        "avatar_url": "https://avatars2.githubusercontent.com/u/423812?v=4",
        "url": "https://api.github.com/users/kekumu",
        "contributions": 1
    },
    {
        "login": "bablakely",
        "avatar_url": "https://avatars1.githubusercontent.com/u/2277811?v=4",
        "url": "https://api.github.com/users/bablakely",
        "contributions": 1
    },
    {
        "login": "lollyrocker",
        "avatar_url": "https://avatars0.githubusercontent.com/u/5963326?v=4",
        "url": "https://api.github.com/users/lollyrocker",
        "contributions": 1
    },
    {
        "login": "phillym",
        "avatar_url": "https://avatars1.githubusercontent.com/u/10522109?v=4",
        "url": "https://api.github.com/users/phillym",
        "contributions": 1
    },
    {
        "login": "krhubert",
        "avatar_url": "https://avatars2.githubusercontent.com/u/1803915?v=4",
        "url": "https://api.github.com/users/krhubert",
        "contributions": 1
    },
    {
        "login": "vibrato-chris-automate",
        "avatar_url": "https://avatars0.githubusercontent.com/u/30867996?v=4",
        "url": "https://api.github.com/users/vibrato-chris-automate",
        "contributions": 1
    },
    {
        "login": "manuelprinz",
        "avatar_url": "https://avatars2.githubusercontent.com/u/8405042?v=4",
        "url": "https://api.github.com/users/manuelprinz",
        "contributions": 1
    },
    {
        "login": "kravietz",
        "avatar_url": "https://avatars2.githubusercontent.com/u/616047?v=4",
        "url": "https://api.github.com/users/kravietz",
        "contributions": 1
    },
    {
        "login": "claw-ss",
        "avatar_url": "https://avatars1.githubusercontent.com/u/14905135?v=4",
        "url": "https://api.github.com/users/claw-ss",
        "contributions": 1
    },
    {
        "login": "danieldreier",
        "avatar_url": "https://avatars1.githubusercontent.com/u/5070204?v=4",
        "url": "https://api.github.com/users/danieldreier",
        "contributions": 1
    },
    {
        "login": "spielkind",
        "avatar_url": "https://avatars3.githubusercontent.com/u/4437264?v=4",
        "url": "https://api.github.com/users/spielkind",
        "contributions": 1
    },
    {
        "login": "Zordrak",
        "avatar_url": "https://avatars3.githubusercontent.com/u/151241?v=4",
        "url": "https://api.github.com/users/Zordrak",
        "contributions": 1
    },
    {
        "login": "vishesh92",
        "avatar_url": "https://avatars0.githubusercontent.com/u/8760112?v=4",
        "url": "https://api.github.com/users/vishesh92",
        "contributions": 1
    },
    {
        "login": "gdestuynder",
        "avatar_url": "https://avatars3.githubusercontent.com/u/956866?v=4",
        "url": "https://api.github.com/users/gdestuynder",
        "contributions": 1
    },
    {
        "login": "HelioCampos",
        "avatar_url": "https://avatars3.githubusercontent.com/u/1965427?v=4",
        "url": "https://api.github.com/users/HelioCampos",
        "contributions": 1
    },
    {
        "login": "eramoto",
        "avatar_url": "https://avatars3.githubusercontent.com/u/20554219?v=4",
        "url": "https://api.github.com/users/eramoto",
        "contributions": 1
    },
    {
        "login": "brimstone",
        "avatar_url": "https://avatars3.githubusercontent.com/u/812795?v=4",
        "url": "https://api.github.com/users/brimstone",
        "contributions": 1
    },
    {
        "login": "radhus",
        "avatar_url": "https://avatars3.githubusercontent.com/u/1115946?v=4",
        "url": "https://api.github.com/users/radhus",
        "contributions": 1
    },
    {
        "login": "carchrae",
        "avatar_url": "https://avatars1.githubusercontent.com/u/959825?v=4",
        "url": "https://api.github.com/users/carchrae",
        "contributions": 1
    },
    {
        "login": "rhass",
        "avatar_url": "https://avatars2.githubusercontent.com/u/1200379?v=4",
        "url": "https://api.github.com/users/rhass",
        "contributions": 1
    },
    {
        "login": "Viktor-ret",
        "avatar_url": "https://avatars0.githubusercontent.com/u/36506526?v=4",
        "url": "https://api.github.com/users/Viktor-ret",
        "contributions": 1
    },
    {
        "login": "sgrossberndt",
        "avatar_url": "https://avatars2.githubusercontent.com/u/3786510?v=4",
        "url": "https://api.github.com/users/sgrossberndt",
        "contributions": 1
    },
    {
        "login": "hannah-radish",
        "avatar_url": "https://avatars3.githubusercontent.com/u/18180779?v=4",
        "url": "https://api.github.com/users/hannah-radish",
        "contributions": 1
    },
    {
        "login": "rljohnsn",
        "avatar_url": "https://avatars2.githubusercontent.com/u/830382?v=4",
        "url": "https://api.github.com/users/rljohnsn",
        "contributions": 1
    }
]